{"_path":"/aboutus/ip","_dir":"aboutus","_draft":false,"_partial":false,"_locale":"","title":"事業計画","description":"","body":{"type":"root","children":[{"type":"element","tag":"h2","props":{"id":"令和6年度事業計画"},"children":[{"type":"text","value":"令和6年度　事業計画"}]},{"type":"element","tag":"border-list","props":{},"children":[{"type":"element","tag":"border-list-item","props":{},"children":[{"type":"element","tag":"p","props":{},"children":[{"type":"element","tag":"a","props":{"download":"令和6年度事業計画書.pdf","href":"/docs/R6%E4%BA%8B%E6%A5%AD%E8%A8%88%E7%94%BB.pdf","target":"_blank"},"children":[{"type":"text","value":"令和6年度 事業計画書"}]}]}]}]},{"type":"element","tag":"br","props":{},"children":[]},{"type":"element","tag":"h2","props":{"id":"令和5年度事業計画"},"children":[{"type":"text","value":"令和5年度　事業計画"}]},{"type":"element","tag":"border-list","props":{},"children":[{"type":"element","tag":"border-list-item","props":{},"children":[{"type":"element","tag":"p","props":{},"children":[{"type":"element","tag":"a","props":{"download":"令和5年度事業計画書.pdf","href":"/docs/R5%E4%BA%8B%E6%A5%AD%E8%A8%88%E7%94%BB.pdf","target":"_blank"},"children":[{"type":"text","value":"令和5年度 事業計画書"}]}]}]}]},{"type":"element","tag":"br","props":{},"children":[]},{"type":"element","tag":"h2","props":{"id":"令和4年度事業計画"},"children":[{"type":"text","value":"令和4年度　事業計画"}]},{"type":"element","tag":"border-list","props":{},"children":[{"type":"element","tag":"border-list-item","props":{},"children":[{"type":"element","tag":"p","props":{},"children":[{"type":"element","tag":"a","props":{"download":"令和4年度事業計画書.pdf","href":"/docs/R4%E4%BA%8B%E6%A5%AD%E8%A8%88%E7%94%BB.20220401.pdf","target":"_blank"},"children":[{"type":"text","value":"令和4年度 事業計画書"}]}]}]}]},{"type":"element","tag":"br","props":{},"children":[]},{"type":"element","tag":"h2","props":{"id":"令和3年度事業計画"},"children":[{"type":"text","value":"令和3年度　事業計画"}]},{"type":"element","tag":"border-list","props":{},"children":[{"type":"element","tag":"border-list-item","props":{},"children":[{"type":"element","tag":"p","props":{},"children":[{"type":"element","tag":"a","props":{"download":"令和3年度事業計画書.pdf","href":"/docs/R3%E4%BA%8B%E6%A5%AD%E8%A8%88%E7%94%BB.pdf","target":"_blank"},"children":[{"type":"text","value":"令和3年度 事業計画書"}]}]}]}]}],"toc":{"title":"","searchDepth":2,"depth":2,"links":[{"id":"令和6年度事業計画","depth":2,"text":"令和6年度　事業計画"},{"id":"令和5年度事業計画","depth":2,"text":"令和5年度　事業計画"},{"id":"令和4年度事業計画","depth":2,"text":"令和4年度　事業計画"},{"id":"令和3年度事業計画","depth":2,"text":"令和3年度　事業計画"}]}},"_type":"markdown","_id":"content:aboutus:ip.md","_source":"content","_file":"aboutus/ip.md","_extension":"md"}